_MeCab.cpython-311-x86_64-linux-gnu.so
mecabrc
MeCab.py
mecab_ko_msvc-0.999.data/scripts/mecab-cost-train
mecab_ko_msvc-0.999.data/scripts/add-userdic.sh
mecab_ko_msvc-0.999.data/scripts/mecab
mecab_ko_msvc-0.999.data/scripts/mecab-system-eval
mecab_ko_msvc-0.999.data/scripts/mecab-dict-index
mecab_ko_msvc-0.999.data/scripts/mecab-dict-gen
mecab_ko_msvc-0.999.data/scripts/mecab-test-gen
mecab_ko_msvc-0.999.dist-info/METADATA
mecab_ko_msvc-0.999.dist-info/RECORD
mecab_ko_msvc-0.999.dist-info/WHEEL
