Metadata-Version: 2.1
Name: mecab-ko-msvc
Version: 0.999
Summary: Mecab-ko-msvc build
Maintainer-Email: Wonsup Yoon <wonsup@pusnow.com>
Classifier: Programming Language :: C
Classifier: Programming Language :: Python
Classifier: Programming Language :: Python :: 3
Classifier: Programming Language :: Python :: 3.7
Classifier: Programming Language :: Python :: 3.8
Classifier: Programming Language :: Python :: 3.9
Classifier: Programming Language :: Python :: 3.10
Classifier: Programming Language :: Python :: 3.11
Classifier: Topic :: Software Development :: Libraries
Project-URL: Documentation, https://github.com/Pusnow/mecab-ko-msvc/
Project-URL: Source, https://github.com/Pusnow/mecab-ko-msvc/
Project-URL: Issue tracker, https://github.com/Pusnow/mecab-ko-msvcissues
Requires-Python: >=3.7
